LICENSE
ndl_tools/__init__.py
ndl_tools/differ.py
ndl_tools/formatter.py
ndl_tools/list_sorter.py
ndl_tools/normalizer.py
ndl_tools/selector.py
ndl_tools/sorter.py
ndl_tools-0.0.18.dist-info/LICENSE
ndl_tools-0.0.18.dist-info/WHEEL
ndl_tools-0.0.18.dist-info/METADATA
ndl_tools-0.0.18.dist-info/RECORD
