Metadata-Version: 2.1
Name: ndl-tools
Version: 0.0.18
Summary: Tools for sorting and diffing nested dictionaries and lists.
Home-page: https://github.com/nathan5280/ndl-tools
License: MIT
Keywords: api,testing,diff
Author: Nate Atkins
Author-email: atkinsnw@gmail.com
Requires-Python: >=3.7,<4.0
Classifier: License :: OSI Approved :: MIT License
Classifier: Operating System :: OS Independent
Classifier: Programming Language :: Python :: 3
Classifier: Programming Language :: Python :: 3.7
Classifier: Programming Language :: Python :: 3.8
Classifier: Topic :: Software Development :: Testing :: Unit
Project-URL: Repository, https://github.com/nathan5280/ndl-tools
